{
"HorizonLayout":[
{
"layout":"bannerImage",
"design":"default",
"fit":"cover",
"marginLeft":0.0,
"items":[
{
"image":"https://user-images.githubusercontent.com/1459805/59846818-12672e80-938b-11e9-8184-5f7bfe66f1a2.png",
"showSubcategory":false,
"bannerWithProduct":false,
"defaultShowProduct":false,
"video":"",
"products":[],
"productLength":3
},
{
"image":"https://user-images.githubusercontent.com/1459805/60091575-1f12ca80-976f-11e9-962c-bdccff60d143.png",
"showSubcategory":false,
"bannerWithProduct":false,
"defaultShowProduct":false,
"video":"",
"products":[],
"productLength":3
},
{
"image":"https://user-images.githubusercontent.com/1459805/60091808-a19b8a00-976f-11e9-9cc7-576ca05c2442.png",
"showSubcategory":false,
"bannerWithProduct":false,
"defaultShowProduct":false,
"video":"",
"products":[],
"productLength":3
}
],
"marginBottom":0.0,
"marginRight":0.0,
"marginTop":0.0,
"radius":2.0,
"padding":0.0,
"parallax":false,
"parallaxImageRatio":1.2,
"isHorizontal":false,
"enableBackground":false,
"isSlider":true,
"autoPlay":false,
"intervalTime":0,
"showNumber":false,
"isBlur":false,
"showBackground":false,
"upHeight":0.0,
"isSoundOn":false,
"enableTimeIndicator":true,
"autoPlayVideo":false,
"doubleTapToFullScreen":false,
"pageIndicatorType":"line",
"preview_data":false
},
{
"name":"",
"layout":"staggered",
"isSnapping":true,
"image":"",
"borderRadius":3.0,
"hMargin":6.0,
"useCircularRadius":true,
"useSort":false,
"showCategory":false,
"vMargin":0.0,
"hPadding":0.0,
"vPadding":0.0,
"cardDesign":"card",
"order":"asc",
"orderby":"menu_order",
"backgroundRadius":10.0,
"showCountDown":false,
"onSale":false,
"rows":1,
"columns":0,
"imageRatio":1.2,
"imageBoxfit":"cover",
"hidePrice":false,
"hideStore":false,
"hideTitle":false,
"featured":false,
"enableRating":true,
"showStockStatus":true,
"hideEmptyProductListRating":false,
"showHeart":false,
"showCartButton":false,
"showCartIcon":true,
"showCartIconColor":true,
"cartIconRadius":20.0,
"showQuantity":true,
"enableBottomAddToCart":false,
"showOnlyImage":false,
"showCartButtonWithQuantity":false,
"parallax":false,
"parallaxImageRatio":1.2,
"hideEmptyProductLayout":false,
"productListItemHeight":125.0,
"enableAutoSliding":false,
"preview_data":false
},
{
"name":"",
"layout":"quiltedGridTile",
"isSnapping":false,
"image":"",
"borderRadius":11.0,
"hMargin":6.0,
"useCircularRadius":true,
"useSort":false,
"showCategory":false,
"vMargin":0.0,
"hPadding":0.0,
"vPadding":0.0,
"cardDesign":"card",
"order":"asc",
"orderby":"menu_order",
"backgroundRadius":10.0,
"showCountDown":false,
"onSale":false,
"rows":1,
"columns":0,
"imageRatio":1.7999999999999998,
"imageBoxfit":"contain",
"hidePrice":false,
"hideStore":false,
"hideTitle":true,
"featured":false,
"enableRating":false,
"showStockStatus":false,
"hideEmptyProductListRating":false,
"showHeart":false,
"showCartButton":false,
"showCartIcon":true,
"showCartIconColor":false,
"cartIconRadius":9.0,
"showQuantity":false,
"enableBottomAddToCart":false,
"showOnlyImage":false,
"showCartButtonWithQuantity":false,
"parallax":false,
"parallaxImageRatio":1.2,
"hideEmptyProductLayout":false,
"productListItemHeight":125.0,
"enableAutoSliding":false,
"preview_data":false
},
{
"layout":"bannerImage",
"design":"stack",
"fit":"fitHeight",
"marginLeft":0.0,
"items":[
{
"image":"https://trello.com/1/cards/66a5d39c38e1409aaf46336f/attachments/66a5e87f9446957eff95cd78/download/8207f3049e.jpg"
},
{
"image":"https://trello.com/1/cards/66a5d39c38e1409aaf46336f/attachments/66a5e8ca993fe4ebb8a44c08/download/triangular-long-crystal-diamond-colored-background.jpg"
},
{
"image":"https://trello.com/1/cards/66a5d39c38e1409aaf46336f/attachments/66a5e8bf05742583d6985c54/download/pattern-glass-product-backdrop-with-stand_(3).jpg"
}
],
"marginBottom":0.0,
"height":0.45,
"marginRight":0.0,
"marginTop":10.0,
"radius":0.0,
"padding":0.0,
"title":{
"isSafeArea":false,
"showSearch":false,
"usePrimaryColor":true,
"borderInput":false,
"title":"Title",
"alignment":"centerLeft",
"fontWeight":400,
"fontSize":25,
"textOpacity":1,
"marginLeft":16,
"marginRight":0,
"marginBottom":0,
"marginTop":0,
"paddingLeft":5.0,
"paddingRight":15.0,
"paddingTop":0.0,
"paddingBottom":0.0,
"height":50,
"rotate":[]
},
"isSlider":true,
"autoPlay":true,
"intervalTime":3,
"showNumber":false,
"isBlur":false,
"showBackground":false,
"upHeight":0.0,
"preview_data":false
},
{
"layout":"bannerImage",
"design":"static",
"fit":"fitWidth",
"marginLeft":10.0,
"items":[
{
"padding":5.0,
"image":"https://user-images.githubusercontent.com/1459805/59846823-12ffc500-938b-11e9-8d93-65ead3d6b1dd.png",
"showSubcategory":false,
"bannerWithProduct":false,
"defaultShowProduct":false,
"video":"",
"products":[],
"productLength":3,
"key":"DvARYOjYbE",
"tab":"home"
},
{
"padding":5.0,
"image":"https://user-images.githubusercontent.com/1459805/59846824-12ffc500-938b-11e9-8d5a-fc42cb1b7658.png",
"showSubcategory":false,
"bannerWithProduct":false,
"defaultShowProduct":false,
"video":"",
"products":[],
"productLength":3
}
],
"marginBottom":0.0,
"height":0.25,
"marginRight":10.0,
"marginTop":10.0,
"radius":6.0,
"padding":0.0,
"parallax":false,
"parallaxImageRatio":1.2,
"isHorizontal":false,
"enableBackground":false,
"preview_data":false
}
],
"Setting":{
"MainColor":"#3FC1BE",
"ProductListLayout":"list",
"StickyHeader":true,
"ProductDetail":"simpleType",
"ShowChat":true,
"AgeRestriction":{
"title":"Welcome to our shop\nYou must be 21 or older to enter",
"enable":false,
"useLogo":true,
"imageUrl":"",
"minimumAge":21,
"hintMessage":"What is your year of birth?",
"deniedMessage":"You are not of legal age to use this application",
"alwaysShowUponOpen":true,
"backgroundImageUrl":""
},
"SmartEngagementBanner":{
"popup":{
"data":{
"fit":"fitHeight",
"key":"BZFZHiGAEZ",
"items":[
{
"image":"https://i.imgur.com/ZL1LO75.png",
"video":"",
"padding":0,
"category":"22",
"products":[],
"description":{
"x":0,
"y":-1,
"text":"",
"color":"#3FC1BE",
"fontSize":20,
"fontFamily":"Roboto",
"enableShadow":false
},
"productLength":3,
"showSubcategory":false,
"bannerWithProduct":true,
"defaultShowProduct":false
}
],
"design":"static",
"height":0.45,
"layout":"bannerImage",
"parallax":false,
"boxShadow":null,
"marginTop":10,
"marginLeft":0,
"marginRight":0,
"isHorizontal":false,
"marginBottom":10,
"enableParallax":false,
"enableBackground":false,
"parallaxImageRatio":1.2
},
"enable":false,
"updatedTime":1727443846654,
"closePosition":"bottomCenter",
"alwaysShowUponOpen":true
},
"sticky":{
"data":{
"fit":"cover",
"key":"pKkVlfMArM",
"items":[
{
"image":"https://i.imgur.com/ZhDXYkZ.gif",
"video":"",
"products":[],
"showSubcategory":false,
"bannerWithProduct":false,
"defaultShowProduct":false
},
{
"image":"https://i.imgur.com/jSyDtDq.gif",
"video":"",
"coupon":"",
"products":[],
"showSubcategory":false,
"bannerWithProduct":false,
"defaultShowProduct":false
},
{
"image":"https://i.imgur.com/SNl32jX.gif",
"video":"",
"screen":"login",
"products":[],
"showSubcategory":false,
"bannerWithProduct":false,
"defaultShowProduct":false
},
{
"image":"https://i.imgur.com/zJlGTf6.gif",
"video":"",
"screen":"search",
"products":[],
"showSubcategory":false,
"bannerWithProduct":false,
"defaultShowProduct":false
},
{
"tab":"videos",
"image":"https://i.imgur.com/Um59HX7.gif",
"video":"",
"products":[],
"showSubcategory":false,
"bannerWithProduct":false,
"defaultShowProduct":false
},
{
"tab":"wishlist",
"image":"https://i.imgur.com/lsfPeaP.gif",
"video":"",
"products":[],
"showSubcategory":false,
"bannerWithProduct":false,
"defaultShowProduct":false
},
{
"tab":"category",
"image":"https://i.imgur.com/ImYVhbT.gif",
"video":"",
"products":[],
"showSubcategory":false,
"bannerWithProduct":false,
"defaultShowProduct":false
}
],
"design":"swiper",
"height":0.1,
"isBlur":false,
"layout":"bannerImage",
"radius":3.3,
"padding":0,
"autoPlay":true,
"isSlider":true,
"parallax":false,
"upHeight":0,
"boxShadow":null,
"isSoundOn":false,
"marginTop":1,
"marginLeft":null,
"showNumber":false,
"marginRight":null,
"intervalTime":4,
"isHorizontal":false,
"marginBottom":1,
"autoPlayVideo":false,
"enableParallax":false,
"showBackground":false,
"enableBackground":false,
"pageIndicatorType":"line",
"parallaxImageRatio":1.2,
"enableTimeIndicator":true,
"doubleTapToFullScreen":false
},
"enable":false
},
"flexible":{
"data":{
"key":"DROmaOXPdV",
"items":[
{
"image":"https://vault.bigfix.in/static/assets/images/new.gif",
"width":224,
"height":127,
"navigator":{
"screen":"category",
"fullscreen":true,
"showSubcategory":false
},
"marginLeft":0,
"marginRight":0,
"useMaxWidth":false,
"borderRadius":2,
"textFontSize":14
}
],
"layout":"button",
"alignment":"topLeft",
"marginTop":40,
"marginBottom":43,
"enableBackground":false
},
"width":173,
"enable":true,
"height":190,
"canDrag":true,
"canClose":true}}
},
"TabBar":[
{
"layout":"home",
"icon":"home",
"pos":100,
"fontFamily":"CupertinoIcons",
"key":"p1q235ba14"
},
{
"key":"hwu0rkrizt",
"layout":"category",
"icon":"rectangle_grid_1x2",
"fontFamily":"CupertinoIcons",
"pos":200,
"defaultTab":false,
"fullscreen":false,
"showOriginalColor":false,
"categoryLayout":"sideMenu",
"parallax":false,
"parallaxImageRatio":1.2,
"showSearch":true,
"showQRScan":true
},
{
"key":"2reihs4qzc",
"layout":"videos",
"icon":"videocam_circle",
"fontFamily":"CupertinoIcons",
"pos":300,
"defaultTab":false,
"fullscreen":false,
"showOriginalColor":false
},
{
"pos":400,
"icon":"bag",
"layout":"cart",
"categoryLayout":"cart",
"key":"a2xts0oou6",
"fontFamily":"CupertinoIcons"
},
{
"key":"69jw5yx12d",
"layout":"profile",
"icon":"person",
"fontFamily":"CupertinoIcons",
"pos":500,
"defaultTab":false,
"fullscreen":false,
"showOriginalColor":false,
"showBackground":true,
"styleItem":"flatShadow"
},
{
"key":"YUnlqqvARy",
"layout":"tabMenu",
"icon":"brightness",
"fontFamily":"CupertinoIcons",
"defaultTab":false,
"fullscreen":false,
"showOriginalColor":false
},
{
"key":"FnlaZAwhnl",
"layout":"dynamic",
"icon":"left_chevron",
"fontFamily":"CupertinoIcons",
"label":"পপুলার | Popular",
"visible":true,
"defaultTab":false,
"fullscreen":false,
"showOriginalColor":false,
"configs":{
"key":"FnlaZAwhnl",
"layout":"tabMenu",
"icon":"assets/icons/tabs/icon-heartthin.png",
"defaultTab":false,
"fullscreen":false,
"showOriginalColor":false,
"HorizonLayout":[
{
"name":"",
"layout":"simpleList",
"isSnapping":false,
"image":"",
"borderRadius":3.0,
"hMargin":6.0,
"useCircularRadius":true,
"useSort":false,
"showCategory":false,
"vMargin":0.0,
"hPadding":0.0,
"vPadding":0.0,
"cardDesign":"card",
"order":"asc",
"orderby":"menu_order",
"backgroundRadius":10.0,
"showCountDown":false,
"onSale":false,
"rows":1,
"columns":0,
"imageRatio":1.2,
"imageBoxfit":"cover",
"hidePrice":false,
"hideStore":false,
"hideTitle":false,
"featured":false,
"enableRating":true,
"showStockStatus":true,
"hideEmptyProductListRating":false,
"showHeart":false,
"showCartButton":false,
"showCartIcon":true,
"showCartIconColor":false,
"cartIconRadius":9.0,
"showQuantity":false,
"enableBottomAddToCart":false,
"showOnlyImage":false,
"showCartButtonWithQuantity":false,
"parallax":false,
"parallaxImageRatio":1.2,
"hideEmptyProductLayout":false,
"productListItemHeight":125.0,
"enableAutoSliding":false,
"preview_data":false
}
]
},
"menuLabel":"পপুলার | Popular",
"groupLayout":true
},
{
"key":"rZIErOOCLq",
"layout":"dynamic",
"icon":"right_chevron",
"fontFamily":"CupertinoIcons",
"label":"প্রিমিয়াম শুটকি",
"visible":true,
"defaultTab":false,
"fullscreen":false,
"showOriginalColor":false,
"configs":{
"layout":"static",
"icon":"assets/icons/tabs/icon-heartthin.png",
"data":{
"id":1,
"container":{
"height":0.5,
"image":{
"height":0.5,
"width":1.0,
"url":"https://images.unsplash.com/photo-1584352587534-5763683125b5?ixlib=rb-1.2.1&ixid=eyJhcHBfaWQiOjEyMDd9&auto=format&fit=crop&w=2700&q=80",
"align":{
"x":1.0,
"y":1.0}
},
"header":{
"align":{
"x":-1.0,
"y":0.8
},
"padding":{
"horizontal":20.0,
"vertical":10.0
},
"color":"#FFFFFF",
"background":"#000000",
"text":"About US"}
},
"subHeader":"This is sub heading",
"description":"This is description"
},
"key":"rZIErOOCLq",
"HorizonLayout":[],
"VerticalLayout":{
"name":"",
"layout":"topProducts",
"isSnapping":false,
"image":"",
"borderRadius":3.0,
"hMargin":6.0,
"useCircularRadius":true,
"useSort":false,
"showCategory":false,
"vMargin":0.0,
"hPadding":6.0,
"vPadding":2.0,
"cardDesign":"card",
"order":"asc",
"orderby":"menu_order",
"backgroundRadius":10.0,
"showCountDown":false,
"onSale":false,
"rows":1,
"columns":3,
"imageRatio":1.2,
"imageBoxfit":"cover",
"hidePrice":false,
"hideStore":false,
"hideTitle":false,
"enableRating":true,
"showStockStatus":false,
"hideEmptyProductListRating":false,
"showHeart":false,
"showCartButton":false,
"showCartIcon":true,
"showCartIconColor":false,
"cartIconRadius":9.0,
"showQuantity":false,
"enableBottomAddToCart":false,
"showOnlyImage":false,
"showCartButtonWithQuantity":false,
"parallax":false,
"parallaxImageRatio":1.2,
"hideEmptyProductLayout":false,
"productListItemHeight":125.0,
"enableAutoSliding":false,
"categoryConfig":{
"type":"icon",
"layout":"category"
},
"shuffle":null}
},
"menuLabel":"প্রিমিয়াম শুটকি",
"groupLayout":true
},
{
"key":"AnccxkFhhY",
"layout":"dynamic",
"icon":"down_arrow",
"fontFamily":"CupertinoIcons",
"label":"গুঁড়া মশলা",
"visible":true,
"defaultTab":false,
"fullscreen":false,
"showOriginalColor":false,
"configs":{
"layout":"static",
"icon":"assets/icons/tabs/icon-heartthin.png",
"data":{
"id":1,
"container":{
"height":0.5,
"image":{
"height":0.5,
"width":1.0,
"url":"https://images.unsplash.com/photo-1584352587534-5763683125b5?ixlib=rb-1.2.1&ixid=eyJhcHBfaWQiOjEyMDd9&auto=format&fit=crop&w=2700&q=80",
"align":{
"x":1.0,
"y":1.0}
},
"header":{
"align":{
"x":-1.0,
"y":0.8
},
"padding":{
"horizontal":20.0,
"vertical":10.0
},
"color":"#FFFFFF",
"background":"#000000",
"text":"About US"}
},
"subHeader":"This is sub heading",
"description":"This is description"
},
"key":"AnccxkFhhY",
"HorizonLayout":[],
"VerticalLayout":{
"name":"",
"layout":"columnsWithFilter",
"isSnapping":false,
"image":"",
"borderRadius":3.0,
"hMargin":6.0,
"useCircularRadius":true,
"useSort":false,
"showCategory":false,
"vMargin":0.0,
"hPadding":6.0,
"vPadding":2.0,
"cardDesign":"card",
"order":"asc",
"orderby":"menu_order",
"backgroundRadius":10.0,
"showCountDown":false,
"onSale":false,
"rows":1,
"columns":3,
"imageRatio":1.2,
"imageBoxfit":"cover",
"hidePrice":false,
"hideStore":false,
"hideTitle":false,
"enableRating":true,
"showStockStatus":false,
"hideEmptyProductListRating":false,
"showHeart":false,
"showCartButton":false,
"showCartIcon":true,
"showCartIconColor":false,
"cartIconRadius":9.0,
"showQuantity":false,
"enableBottomAddToCart":false,
"showOnlyImage":false,
"showCartButtonWithQuantity":false,
"parallax":false,
"parallaxImageRatio":1.2,
"hideEmptyProductLayout":false,
"productListItemHeight":125.0,
"enableAutoSliding":false,
"categoryConfig":null,
"shuffle":null}
},
"menuLabel":"গুঁড়া মশলা",
"groupLayout":true
},
{
"key":"pRQXVlqeeN",
"layout":"dynamic",
"icon":"up_arrow",
"fontFamily":"CupertinoIcons",
"label":"সিজনাল | Seasonal",
"defaultTab":false,
"fullscreen":false,
"showOriginalColor":false,
"configs":{
"layout":"static",
"icon":"assets/icons/tabs/icon-heartthin.png",
"data":{
"id":1,
"container":{
"height":0.5,
"image":{
"height":0.5,
"width":1.0,
"url":"https://images.unsplash.com/photo-1584352587534-5763683125b5?ixlib=rb-1.2.1&ixid=eyJhcHBfaWQiOjEyMDd9&auto=format&fit=crop&w=2700&q=80",
"align":{
"x":1.0,
"y":1.0}
},
"header":{
"align":{
"x":-1.0,
"y":0.8
},
"padding":{
"horizontal":20.0,
"vertical":10.0
},
"color":"#FFFFFF",
"background":"#000000",
"text":"About US"}
},
"subHeader":"This is sub heading",
"description":"This is description"
},
"key":"pRQXVlqeeN",
"HorizonLayout":[],
"VerticalLayout":{
"name":"",
"layout":"pinterest",
"isSnapping":false,
"image":"",
"borderRadius":3.0,
"hMargin":6.0,
"useCircularRadius":true,
"useSort":false,
"showCategory":false,
"vMargin":0.0,
"hPadding":6.0,
"vPadding":2.0,
"cardDesign":"card",
"order":"asc",
"orderby":"menu_order",
"backgroundRadius":10.0,
"showCountDown":false,
"onSale":false,
"rows":1,
"columns":3,
"imageRatio":1.2,
"imageBoxfit":"cover",
"hidePrice":false,
"hideStore":false,
"hideTitle":false,
"enableRating":true,
"showStockStatus":false,
"hideEmptyProductListRating":false,
"showHeart":false,
"showCartButton":false,
"showCartIcon":true,
"showCartIconColor":false,
"cartIconRadius":9.0,
"showQuantity":false,
"enableBottomAddToCart":false,
"showOnlyImage":false,
"showCartButtonWithQuantity":false,
"parallax":false,
"parallaxImageRatio":1.2,
"hideEmptyProductLayout":false,
"productListItemHeight":125.0,
"enableAutoSliding":false,
"categoryConfig":null,
"shuffle":null}
},
"menuLabel":"সিজনাল | Seasonal",
"groupLayout":true
}
],
"AppBar":null,
"Drawer":{
"items":[
{
"type":"home",
"show":true
},
{
"type":"blog",
"show":true
},
{
"type":"login",
"show":true
},
{
"type":"category",
"show":true
}
]}}
